{
  "id": "cern_m24128_dfmn6",
  "name": "M24128-DFMN6 (CERN library)",
  "category": "ic",
  "family": "CERN Logic",
  "manufacturer": "ST MICROELECTRONICS",
  "mpn_pattern": "M24128-DFMN6",
  "description": "1.7V-5.5V, 128-Kbit Serial I2C bus EEPROM with Unique Identifier. Imported from the CERN KiCad library (CERN-OHL-P-2.0, (c) CERN); passed PartReel quality gates. 3D model generated parametrically from the IPC-7351 package name and the footprint's own pad geometry (PartReel).",
  "parameters": {
    "contacts": "8",
    "mounting": "SMD",
    "case": "MSOP8"
  },
  "files": {
    "footprint": "cern_m24128_dfmn6.kicad_mod",
    "symbol": "cern_m24128_dfmn6.kicad_sym",
    "footprint_svg": "cern_m24128_dfmn6.footprint.svg",
    "symbol_svg": "cern_m24128_dfmn6.symbol.svg",
    "model_3d": "cern_m24128_dfmn6.step",
    "preview": "cern_m24128_dfmn6.glb"
  },
  "formats": [
    "kicad_mod",
    "kicad_sym",
    "step",
    "glb"
  ],
  "datasheet": "https://gitlab.com/ohwr/cern-kicad-libs/-/blob/master/SchLib/Logic.kicad_sym",
  "dimensions_source": "cern-kicad-libs@53054c17 (ICs And Semiconductors SMD.pretty/SOP65P490X110-8N.kicad_mod)",
  "verified": true,
  "origin": "imported",
  "license": "CERN-OHL-P-2.0",
  "generated_by": "generators/import_cern.py",
  "keywords": [
    "cern",
    "128",
    "kbit",
    "serial",
    "i2c",
    "bus",
    "eeprom"
  ],
  "import": {
    "source_repo": "https://gitlab.com/ohwr/cern-kicad-libs",
    "source_commit": "53054c17",
    "source_files": {
      "db": "CERN.sqlite#Logic#M24128-DFMN6",
      "symbol": "SchLib/Logic.kicad_sym#M24128-DFMN6",
      "footprint": "PcbLib/ICs And Semiconductors SMD.pretty/SOP65P490X110-8N.kicad_mod"
    },
    "attribution": "CERN (kicad-dev@cern.ch), CERN-OHL-P-2.0",
    "import_date": "2026-07-05",
    "modifications": [
      "extracted single symbol from library",
      "stripped dead 3D model reference (upstream ships no 3D)",
      "parametric 3D (STEP/GLB) generated by PartReel from IPC package name + pad geometry"
    ]
  },
  "asset_sha256": {
    "cern_m24128_dfmn6.step": "adf4186c97a76abd6637ee461fca08cb9d0d00fba3ea96b67e2cfacf55027744",
    "cern_m24128_dfmn6.glb": "e17b031ed7e493005aadc667f825834252e250d7eac7188cd438bf9b613eb17e"
  }
}