{
  "id": "cern_tps62913rpu",
  "name": "TPS62913RPU (CERN library)",
  "category": "ic",
  "family": "CERN Regulators",
  "manufacturer": "TEXAS INSTRUMENTS",
  "mpn_pattern": "TPS62913RPU",
  "description": "3V to 17V, 3A Low Noise and Low Ripple Buck Converter with Integrated Ferrite Bead Filter Compensation. Imported from the CERN KiCad library (CERN-OHL-P-2.0, (c) CERN); passed PartReel quality gates. Verified-2D part: upstream ships no 3D models.",
  "parameters": {
    "contacts": "10",
    "mounting": "SMD",
    "case": "QFN10"
  },
  "files": {
    "footprint": "cern_tps62913rpu.kicad_mod",
    "symbol": "cern_tps62913rpu.kicad_sym",
    "footprint_svg": "cern_tps62913rpu.footprint.svg",
    "symbol_svg": "cern_tps62913rpu.symbol.svg"
  },
  "formats": [
    "kicad_mod",
    "kicad_sym"
  ],
  "datasheet": "https://gitlab.com/ohwr/cern-kicad-libs/-/blob/master/SchLib/Regulators.kicad_sym",
  "dimensions_source": "cern-kicad-libs@53054c17 (ICs And Semiconductors SMD.pretty/TEXAS_RPU0010A.kicad_mod)",
  "verified": true,
  "origin": "imported",
  "tier": "verified-2d",
  "license": "CERN-OHL-P-2.0",
  "generated_by": "generators/import_cern.py",
  "keywords": [
    "cern",
    "17v",
    "low",
    "noise",
    "and",
    "low",
    "ripple"
  ],
  "import": {
    "source_repo": "https://gitlab.com/ohwr/cern-kicad-libs",
    "source_commit": "53054c17",
    "source_files": {
      "db": "CERN.sqlite#Regulators#TPS62913RPU",
      "symbol": "SchLib/Regulators.kicad_sym#TPS6291x",
      "footprint": "PcbLib/ICs And Semiconductors SMD.pretty/TEXAS_RPU0010A.kicad_mod"
    },
    "attribution": "CERN (kicad-dev@cern.ch), CERN-OHL-P-2.0",
    "import_date": "2026-07-05",
    "modifications": [
      "extracted single symbol from library",
      "stripped dead 3D model reference (upstream ships no 3D)"
    ]
  }
}