{
  "id": "cern_ltc2654cuf_l12_pbf",
  "name": "LTC2654CUF-L12 (CERN library)",
  "category": "ic",
  "family": "CERN Analog & Interface",
  "manufacturer": "LINEAR TECHNOLOGY",
  "mpn_pattern": "LTC2654CUF-L12",
  "description": "Quad 12-Bit Rail-to-Rail DACs with 10ppm/°C Max Reference. Imported from the CERN KiCad library (CERN-OHL-P-2.0, (c) CERN); passed PartReel quality gates. Verified-2D part: upstream ships no 3D models.",
  "parameters": {
    "contacts": "21",
    "mounting": "SMD",
    "case": "QFN20"
  },
  "files": {
    "footprint": "cern_ltc2654cuf_l12_pbf.kicad_mod",
    "symbol": "cern_ltc2654cuf_l12_pbf.kicad_sym",
    "footprint_svg": "cern_ltc2654cuf_l12_pbf.footprint.svg",
    "symbol_svg": "cern_ltc2654cuf_l12_pbf.symbol.svg"
  },
  "formats": [
    "kicad_mod",
    "kicad_sym"
  ],
  "datasheet": "https://gitlab.com/ohwr/cern-kicad-libs/-/blob/master/SchLib/Analog & Interface.kicad_sym",
  "dimensions_source": "cern-kicad-libs@53054c17 (ICs And Semiconductors SMD.pretty/QFN50P400X400X80-21N-S255.kicad_mod)",
  "verified": true,
  "origin": "imported",
  "tier": "verified-2d",
  "license": "CERN-OHL-P-2.0",
  "generated_by": "generators/import_cern.py",
  "keywords": [
    "cern",
    "quad",
    "bit",
    "rail",
    "rail",
    "dacs",
    "with"
  ],
  "import": {
    "source_repo": "https://gitlab.com/ohwr/cern-kicad-libs",
    "source_commit": "53054c17",
    "source_files": {
      "db": "CERN.sqlite#Analog & Interface#LTC2654CUF-L12#PBF",
      "symbol": "SchLib/Analog & Interface.kicad_sym#LTC2654CUF",
      "footprint": "PcbLib/ICs And Semiconductors SMD.pretty/QFN50P400X400X80-21N-S255.kicad_mod"
    },
    "attribution": "CERN (kicad-dev@cern.ch), CERN-OHL-P-2.0",
    "import_date": "2026-07-05",
    "modifications": [
      "extracted single symbol from library",
      "stripped dead 3D model reference (upstream ships no 3D)"
    ]
  }
}