{
  "id": "cern_lt1930es5_pbf",
  "name": "LT1930ES5 (CERN library)",
  "category": "ic",
  "family": "CERN Regulators",
  "manufacturer": "LINEAR TECHNOLOGY",
  "mpn_pattern": "LT1930ES5",
  "description": "(2.6V to +16V) Input  to (-0.4V to 36V) Output, 1A, 1.2MHz Step-Up DC-DC Converters. Imported from the CERN KiCad library (CERN-OHL-P-2.0, (c) CERN); passed PartReel quality gates. 3D model generated parametrically from the IPC-7351 package name and the footprint's own pad geometry (PartReel).",
  "parameters": {
    "contacts": "5",
    "mounting": "SMD",
    "case": "SOT23-5"
  },
  "files": {
    "footprint": "cern_lt1930es5_pbf.kicad_mod",
    "symbol": "cern_lt1930es5_pbf.kicad_sym",
    "footprint_svg": "cern_lt1930es5_pbf.footprint.svg",
    "symbol_svg": "cern_lt1930es5_pbf.symbol.svg",
    "model_3d": "cern_lt1930es5_pbf.step",
    "preview": "cern_lt1930es5_pbf.glb"
  },
  "formats": [
    "kicad_mod",
    "kicad_sym",
    "step",
    "glb"
  ],
  "datasheet": "https://gitlab.com/ohwr/cern-kicad-libs/-/blob/master/SchLib/Regulators.kicad_sym",
  "dimensions_source": "cern-kicad-libs@53054c17 (ICs And Semiconductors SMD.pretty/SOT95P280X100-5N.kicad_mod)",
  "verified": true,
  "origin": "imported",
  "license": "CERN-OHL-P-2.0",
  "generated_by": "generators/import_cern.py",
  "keywords": [
    "cern",
    "16v",
    "input",
    "36v",
    "output",
    "2mhz",
    "step"
  ],
  "import": {
    "source_repo": "https://gitlab.com/ohwr/cern-kicad-libs",
    "source_commit": "53054c17",
    "source_files": {
      "db": "CERN.sqlite#Regulators#LT1930ES5#PBF",
      "symbol": "SchLib/Regulators.kicad_sym#LT1930",
      "footprint": "PcbLib/ICs And Semiconductors SMD.pretty/SOT95P280X100-5N.kicad_mod"
    },
    "attribution": "CERN (kicad-dev@cern.ch), CERN-OHL-P-2.0",
    "import_date": "2026-07-05",
    "modifications": [
      "extracted single symbol from library",
      "stripped dead 3D model reference (upstream ships no 3D)",
      "parametric 3D (STEP/GLB) generated by PartReel from IPC package name + pad geometry"
    ]
  },
  "asset_sha256": {
    "cern_lt1930es5_pbf.step": "2effd88872ccd3e36e45bdb001b1993cbe8721ce42d959d2a95a61a14c555e11",
    "cern_lt1930es5_pbf.glb": "91a0a18d7e182d5af13b38e855c1d08291b2ab272657b7a13044851a40c4c2a8"
  }
}