{
  "id": "cern_cc0805_10nf_500v_10_x7r_yageo_mid_voltage",
  "name": "222297015636 or CC0805KKX7RBBB103 (CERN library)",
  "category": "passive",
  "family": "CERN Capacitors SMD",
  "manufacturer": "YAGEO",
  "mpn_pattern": "222297015636 or CC0805KKX7RBBB103",
  "description": "SMD Multilayer Chip Ceramic Capacitor. Imported from the CERN KiCad library (CERN-OHL-P-2.0, (c) CERN); passed PartReel quality gates. 3D model generated parametrically from the IPC-7351 package name and the footprint's own pad geometry (PartReel). Lifecycle status: Preferred.",
  "parameters": {
    "contacts": 2.0,
    "mounting": "SMD",
    "case": "0805",
    "value": "10nF",
    "lifecycle": "Preferred"
  },
  "formats": [
    "kicad_mod",
    "kicad_sym",
    "step",
    "glb"
  ],
  "files": {
    "footprint": "https://partreel.com/library/passive/cern/cern_cc0805_10nf_500v_10_x7r_yageo_mid_voltage/cern_cc0805_10nf_500v_10_x7r_yageo_mid_voltage.kicad_mod",
    "symbol": "https://partreel.com/library/passive/cern/cern_cc0805_10nf_500v_10_x7r_yageo_mid_voltage/cern_cc0805_10nf_500v_10_x7r_yageo_mid_voltage.kicad_sym",
    "footprint_svg": "https://partreel.com/library/passive/cern/cern_cc0805_10nf_500v_10_x7r_yageo_mid_voltage/cern_cc0805_10nf_500v_10_x7r_yageo_mid_voltage.footprint.svg",
    "symbol_svg": "https://partreel.com/library/passive/cern/cern_cc0805_10nf_500v_10_x7r_yageo_mid_voltage/cern_cc0805_10nf_500v_10_x7r_yageo_mid_voltage.symbol.svg",
    "model_3d": "https://assets.partreel.com/library/passive/cern/cern_cc0805_10nf_500v_10_x7r_yageo_mid_voltage/cern_cc0805_10nf_500v_10_x7r_yageo_mid_voltage.step",
    "preview": "https://assets.partreel.com/library/passive/cern/cern_cc0805_10nf_500v_10_x7r_yageo_mid_voltage/cern_cc0805_10nf_500v_10_x7r_yageo_mid_voltage.glb"
  },
  "datasheet": "https://gitlab.com/ohwr/cern-kicad-libs/-/blob/master/SchLib/Capacitors.kicad_sym",
  "license": "CERN-OHL-P-2.0",
  "verified": true,
  "tier": null,
  "dimensions_source": "cern-kicad-libs@53054c17 (Capacitors SMD.pretty/CAPC2013X145N.kicad_mod)",
  "keywords": [
    "cern",
    "smd",
    "multilayer",
    "chip",
    "ceramic",
    "capacitor"
  ],
  "field_reports": {
    "worked": 0,
    "problem": 0
  },
  "provenance": {
    "dimensions_source": "cern-kicad-libs@53054c17 (Capacitors SMD.pretty/CAPC2013X145N.kicad_mod)",
    "datasheet": "https://gitlab.com/ohwr/cern-kicad-libs/-/blob/master/SchLib/Capacitors.kicad_sym",
    "generator_source": "https://github.com/mingyo186/partreel/blob/main/generators/import_cern.py",
    "quality_gates": {
      "gates": [
        "validate_kicad (structure/pads/layers)",
        "KLC drawing rules (silk/fab/courtyard/pin1)",
        "check_overlap (text collisions)",
        "check_render (files/SVG-vs-source/meta completeness)",
        "check_zfight (3D coplanar faces, merged pins)",
        "validate_step (FreeCAD kernel isValid)"
      ],
      "enforcement": "CI runs all gates on every push and blocks deployment on any failure",
      "ci_config": "https://github.com/mingyo186/partreel/blob/main/.github/workflows/deploy.yml"
    },
    "field_reports": {
      "worked": 0,
      "problem": 0
    },
    "origin": "imported",
    "import": {
      "source_repo": "https://gitlab.com/ohwr/cern-kicad-libs",
      "source_commit": "53054c17",
      "source_files": {
        "db": "CERN.sqlite#Capacitors SMD#CC0805_10NF_500V_10%_X7R_YAGEO_MID-VOLTAGE",
        "symbol": "SchLib/Capacitors.kicad_sym#Capacitor - non polarized",
        "footprint": "PcbLib/Capacitors SMD.pretty/CAPC2013X145N.kicad_mod"
      },
      "attribution": "CERN (kicad-dev@cern.ch), CERN-OHL-P-2.0",
      "import_date": "2026-07-05",
      "modifications": [
        "extracted single symbol from library",
        "stripped dead 3D model reference (upstream ships no 3D)",
        "parametric 3D (STEP/GLB) generated by PartReel from IPC package name + pad geometry"
      ]
    }
  },
  "page": "https://partreel.com/p/cern_cc0805_10nf_500v_10_x7r_yageo_mid_voltage/",
  "api": "https://partreel.com/api/v1/parts/cern_cc0805_10nf_500v_10_x7r_yageo_mid_voltage.json"
}