{
  "id": "cern_cc0402_1_5pf_50v_0_1pf_c0g_murata_gjm1555c1h1r5bb01",
  "name": "GJM1555C1H1R5BB01 (CERN library)",
  "category": "passive",
  "family": "CERN Capacitors SMD",
  "manufacturer": "MURATA",
  "mpn_pattern": "GJM1555C1H1R5BB01",
  "description": "High-Q SMD Chip Multilayer Ceramic Capacitor for General Purpose. Imported from the CERN KiCad library (CERN-OHL-P-2.0, (c) CERN); passed PartReel quality gates. Verified-2D part: upstream ships no 3D models. Lifecycle status: None.",
  "parameters": {
    "contacts": 2.0,
    "mounting": "SMD",
    "case": "0402",
    "value": "1.5pF",
    "lifecycle": "None"
  },
  "formats": [
    "kicad_mod",
    "kicad_sym"
  ],
  "files": {
    "footprint": "https://partreel.com/library/passive/cern/cern_cc0402_1_5pf_50v_0_1pf_c0g_murata_gjm1555c1h1r5bb01/cern_cc0402_1_5pf_50v_0_1pf_c0g_murata_gjm1555c1h1r5bb01.kicad_mod",
    "symbol": "https://partreel.com/library/passive/cern/cern_cc0402_1_5pf_50v_0_1pf_c0g_murata_gjm1555c1h1r5bb01/cern_cc0402_1_5pf_50v_0_1pf_c0g_murata_gjm1555c1h1r5bb01.kicad_sym",
    "footprint_svg": "https://partreel.com/library/passive/cern/cern_cc0402_1_5pf_50v_0_1pf_c0g_murata_gjm1555c1h1r5bb01/cern_cc0402_1_5pf_50v_0_1pf_c0g_murata_gjm1555c1h1r5bb01.footprint.svg",
    "symbol_svg": "https://partreel.com/library/passive/cern/cern_cc0402_1_5pf_50v_0_1pf_c0g_murata_gjm1555c1h1r5bb01/cern_cc0402_1_5pf_50v_0_1pf_c0g_murata_gjm1555c1h1r5bb01.symbol.svg"
  },
  "datasheet": "https://gitlab.com/ohwr/cern-kicad-libs/-/blob/master/SchLib/Capacitors.kicad_sym",
  "license": "CERN-OHL-P-2.0",
  "verified": true,
  "tier": "verified-2d",
  "dimensions_source": "cern-kicad-libs@53054c17 (Capacitors SMD.pretty/CAPC1005X55N.kicad_mod)",
  "keywords": [
    "cern",
    "high",
    "smd",
    "chip",
    "multilayer",
    "ceramic",
    "capacitor"
  ],
  "field_reports": {
    "worked": 0,
    "problem": 0
  },
  "provenance": {
    "dimensions_source": "cern-kicad-libs@53054c17 (Capacitors SMD.pretty/CAPC1005X55N.kicad_mod)",
    "datasheet": "https://gitlab.com/ohwr/cern-kicad-libs/-/blob/master/SchLib/Capacitors.kicad_sym",
    "generator_source": "https://github.com/mingyo186/partreel/blob/main/generators/import_cern.py",
    "quality_gates": {
      "gates": [
        "validate_kicad (structure/pads/layers)",
        "KLC drawing rules (silk/fab/courtyard/pin1)",
        "check_overlap (text collisions)",
        "check_render (files/SVG-vs-source/meta completeness)",
        "check_zfight (3D coplanar faces, merged pins)",
        "validate_step (FreeCAD kernel isValid)"
      ],
      "enforcement": "CI runs all gates on every push and blocks deployment on any failure",
      "ci_config": "https://github.com/mingyo186/partreel/blob/main/.github/workflows/deploy.yml"
    },
    "field_reports": {
      "worked": 0,
      "problem": 0
    },
    "origin": "imported",
    "import": {
      "source_repo": "https://gitlab.com/ohwr/cern-kicad-libs",
      "source_commit": "53054c17",
      "source_files": {
        "db": "CERN.sqlite#Capacitors SMD#CC0402_1.5PF_50V_0.1PF_C0G_MURATA_GJM1555C1H1R5BB01",
        "symbol": "SchLib/Capacitors.kicad_sym#Capacitor - non polarized",
        "footprint": "PcbLib/Capacitors SMD.pretty/CAPC1005X55N.kicad_mod"
      },
      "attribution": "CERN (kicad-dev@cern.ch), CERN-OHL-P-2.0",
      "import_date": "2026-07-05",
      "modifications": [
        "extracted single symbol from library",
        "stripped dead 3D model reference (upstream ships no 3D)"
      ]
    }
  },
  "page": "https://partreel.com/p/cern_cc0402_1_5pf_50v_0_1pf_c0g_murata_gjm1555c1h1r5bb01/",
  "api": "https://partreel.com/api/v1/parts/cern_cc0402_1_5pf_50v_0_1pf_c0g_murata_gjm1555c1h1r5bb01.json"
}