{
  "id": "cern_cy7c1314kv18_250bzxc",
  "name": "CY7C1314KV18-250BZXC (CERN library)",
  "category": "ic",
  "family": "CERN Logic",
  "manufacturer": "CYPRESS",
  "mpn_pattern": "CY7C1314KV18-250BZXC",
  "description": "1.8V, 250MHz, 18-Mbit (512k X 36) QDR®II SRAM 2-Word Burst Architecture. Imported from the CERN KiCad library (CERN-OHL-P-2.0, (c) CERN); passed PartReel quality gates. 3D model generated parametrically from the IPC-7351 package name and the footprint's own pad geometry (PartReel).",
  "parameters": {
    "contacts": "165",
    "mounting": "SMD",
    "case": "BGA165"
  },
  "files": {
    "footprint": "cern_cy7c1314kv18_250bzxc.kicad_mod",
    "symbol": "cern_cy7c1314kv18_250bzxc.kicad_sym",
    "footprint_svg": "cern_cy7c1314kv18_250bzxc.footprint.svg",
    "symbol_svg": "cern_cy7c1314kv18_250bzxc.symbol.svg",
    "model_3d": "cern_cy7c1314kv18_250bzxc.step",
    "preview": "cern_cy7c1314kv18_250bzxc.glb"
  },
  "formats": [
    "kicad_mod",
    "kicad_sym",
    "step",
    "glb"
  ],
  "datasheet": "https://gitlab.com/ohwr/cern-kicad-libs/-/blob/master/SchLib/Logic.kicad_sym",
  "dimensions_source": "cern-kicad-libs@53054c17 (ICs And Semiconductors SMD_BGA.pretty/BGA165C100P11X15_1300X1500X140.kicad_mod)",
  "verified": true,
  "origin": "imported",
  "license": "CERN-OHL-P-2.0",
  "generated_by": "generators/import_cern.py",
  "keywords": [
    "cern",
    "250mhz",
    "mbit",
    "512k",
    "qdr",
    "sram",
    "word"
  ],
  "import": {
    "source_repo": "https://gitlab.com/ohwr/cern-kicad-libs",
    "source_commit": "53054c17",
    "source_files": {
      "db": "CERN.sqlite#Logic#CY7C1314KV18-250BZXC",
      "symbol": "SchLib/Logic.kicad_sym#CY7C1314KV18-250BZXC",
      "footprint": "PcbLib/ICs And Semiconductors SMD_BGA.pretty/BGA165C100P11X15_1300X1500X140.kicad_mod"
    },
    "attribution": "CERN (kicad-dev@cern.ch), CERN-OHL-P-2.0",
    "import_date": "2026-07-05",
    "modifications": [
      "extracted single symbol from library",
      "stripped dead 3D model reference (upstream ships no 3D)",
      "parametric 3D (STEP/GLB) generated by PartReel from IPC package name + pad geometry"
    ]
  },
  "asset_sha256": {
    "cern_cy7c1314kv18_250bzxc.step": "aaf96fb0c897befd924990789b1a7424ac5e6034b109da7eb909368c28012dae",
    "cern_cy7c1314kv18_250bzxc.glb": "c1737c80e6a803e8435e5c41703936858f6712e5ad5b543a2ada4a78bfa2ea37"
  }
}