{
  "id": "cern_2edf7175fxuma2",
  "name": "2EDF7175FXUMA2 (CERN library)",
  "category": "ic",
  "family": "CERN Analog & Interface",
  "manufacturer": "INFINEON",
  "mpn_pattern": "2EDF7175FXUMA2",
  "description": "Fast, Robust, Dual-Channel, Functional and Reinforced Isolated, MOSFET Gate-Driver with Accurate and Stable Timing. Imported from the CERN KiCad library (CERN-OHL-P-2.0, (c) CERN); passed PartReel quality gates. Verified-2D part: upstream ships no 3D models.",
  "parameters": {
    "contacts": "16",
    "mounting": "SMD",
    "case": "SOIC16"
  },
  "files": {
    "footprint": "cern_2edf7175fxuma2.kicad_mod",
    "symbol": "cern_2edf7175fxuma2.kicad_sym",
    "footprint_svg": "cern_2edf7175fxuma2.footprint.svg",
    "symbol_svg": "cern_2edf7175fxuma2.symbol.svg"
  },
  "formats": [
    "kicad_mod",
    "kicad_sym"
  ],
  "datasheet": "https://gitlab.com/ohwr/cern-kicad-libs/-/blob/master/SchLib/Analog & Interface.kicad_sym",
  "dimensions_source": "cern-kicad-libs@53054c17 (ICs And Semiconductors SMD.pretty/SOIC127P600X175-16N.kicad_mod)",
  "verified": true,
  "origin": "imported",
  "tier": "verified-2d",
  "license": "CERN-OHL-P-2.0",
  "generated_by": "generators/import_cern.py",
  "keywords": [
    "cern",
    "fast",
    "robust",
    "dual",
    "channel",
    "functional",
    "and"
  ],
  "import": {
    "source_repo": "https://gitlab.com/ohwr/cern-kicad-libs",
    "source_commit": "53054c17",
    "source_files": {
      "db": "CERN.sqlite#Analog & Interface#2EDF7175FXUMA2",
      "symbol": "SchLib/Analog & Interface.kicad_sym#2EDF7175F",
      "footprint": "PcbLib/ICs And Semiconductors SMD.pretty/SOIC127P600X175-16N.kicad_mod"
    },
    "attribution": "CERN (kicad-dev@cern.ch), CERN-OHL-P-2.0",
    "import_date": "2026-07-05",
    "modifications": [
      "extracted single symbol from library",
      "stripped dead 3D model reference (upstream ships no 3D)"
    ]
  }
}