{
  "id": "cern_max921cua",
  "name": "MAX921CUA (CERN library)",
  "category": "ic",
  "family": "CERN Op Amps",
  "manufacturer": "MAXIM",
  "mpn_pattern": "MAX921CUA",
  "description": "Ultra Low-Power, Single-Supply Comparator. Imported from the CERN KiCad library (CERN-OHL-P-2.0, (c) CERN); passed PartReel quality gates. 3D model generated parametrically from the IPC-7351 package name and the footprint's own pad geometry (PartReel).",
  "parameters": {
    "contacts": "8",
    "mounting": "SMD",
    "case": "TSSPO8"
  },
  "files": {
    "footprint": "cern_max921cua.kicad_mod",
    "symbol": "cern_max921cua.kicad_sym",
    "footprint_svg": "cern_max921cua.footprint.svg",
    "symbol_svg": "cern_max921cua.symbol.svg",
    "model_3d": "cern_max921cua.step",
    "preview": "cern_max921cua.glb"
  },
  "formats": [
    "kicad_mod",
    "kicad_sym",
    "step",
    "glb"
  ],
  "datasheet": "https://gitlab.com/ohwr/cern-kicad-libs/-/blob/master/SchLib/Operational Amplifiers.kicad_sym",
  "dimensions_source": "cern-kicad-libs@53054c17 (ICs And Semiconductors SMD.pretty/SOP65P490X110-8N.kicad_mod)",
  "verified": true,
  "origin": "imported",
  "license": "CERN-OHL-P-2.0",
  "generated_by": "generators/import_cern.py",
  "keywords": [
    "cern",
    "ultra",
    "low",
    "power",
    "single",
    "supply",
    "comparator"
  ],
  "import": {
    "source_repo": "https://gitlab.com/ohwr/cern-kicad-libs",
    "source_commit": "53054c17",
    "source_files": {
      "db": "CERN.sqlite#Operational Amplifiers#MAX921CUA+",
      "symbol": "SchLib/Operational Amplifiers.kicad_sym#MAX921",
      "footprint": "PcbLib/ICs And Semiconductors SMD.pretty/SOP65P490X110-8N.kicad_mod"
    },
    "attribution": "CERN (kicad-dev@cern.ch), CERN-OHL-P-2.0",
    "import_date": "2026-07-05",
    "modifications": [
      "extracted single symbol from library",
      "stripped dead 3D model reference (upstream ships no 3D)",
      "parametric 3D (STEP/GLB) generated by PartReel from IPC package name + pad geometry"
    ]
  },
  "asset_sha256": {
    "cern_max921cua.step": "d97f410cd69b9522d03f14e606daca9a7b083f88cb7d8f4c94384fb5817dc4af",
    "cern_max921cua.glb": "e17b031ed7e493005aadc667f825834252e250d7eac7188cd438bf9b613eb17e"
  }
}