{
  "id": "screw_terminal_5_08_2pin",
  "name": "Screw Terminal 5.08mm 2-pin (KF301-5.08-2P)",
  "category": "connector",
  "family": "Screw Terminal 5.08mm",
  "manufacturer": "Generic (KF301)",
  "mpn_pattern": "KF301-5.08-2P",
  "description": "5.08mm pitch 2-pole screw terminal block (KF301-compatible), THT. For power and wire-to-board connections.",
  "parameters": {
    "pitch_mm": 5.08,
    "pins": 2,
    "mounting": "THT",
    "orientation": "vertical"
  },
  "files": {
    "footprint": "screw_terminal_5_08_2pin.kicad_mod",
    "symbol": "screw_terminal_5_08_2pin.kicad_sym",
    "model_3d": "screw_terminal_5_08_2pin.step",
    "preview": "screw_terminal_5_08_2pin.glb",
    "footprint_svg": "screw_terminal_5_08_2pin.footprint.svg",
    "symbol_svg": "screw_terminal_5_08_2pin.symbol.svg"
  },
  "formats": [
    "kicad_mod",
    "kicad_sym",
    "step",
    "glb"
  ],
  "datasheet": "https://datasheet.lcsc.com/lcsc/1811141810_Cixi-Kefa-Rongda-KF301-5-0-2P_C8465.pdf",
  "dimensions_source": "Pad land pattern matches KiCad official TerminalBlock_bornier P5.08mm (pad 3.0, drill 1.52). Body/3D representative of KF301-type blocks.",
  "verified": true,
  "license": "CC-BY-4.0",
  "generated_by": "generators/gen_connectors.py",
  "keywords": [
    "screw",
    "terminal",
    "5.08mm",
    "connector",
    "2pin"
  ],
  "asset_sha256": {
    "screw_terminal_5_08_2pin.step": "c474087f3bd5c7c2700ec57effd8ffd4a2c963999f8e247959520389f3f43e63",
    "screw_terminal_5_08_2pin.glb": "63493d4e746a539baff4165b67b34cda303c9952b1e1305e824fe5c4e7abc0c2"
  }
}