{
  "id": "cern_rn_50m_metallux_hvd_967_15_51_b_50m_1_1000_1_tc_50_25",
  "name": "HVD 967.15.51 B 50M 1:1000 1% TC 50/25 (CERN library)",
  "category": "passive",
  "family": "CERN Resistor Networks THD",
  "manufacturer": "METALLUX",
  "mpn_pattern": "HVD 967.15.51 B 50M 1:1000 1% TC 50/25",
  "description": "High Voltage Divider HVD NW Series 967.15.51 Type. Imported from the CERN KiCad library (CERN-OHL-P-2.0, (c) CERN); passed PartReel quality gates. Verified-2D part: upstream ships no 3D models. Lifecycle status: Not recommended.",
  "parameters": {
    "contacts": "3",
    "value": "50M",
    "lifecycle": "Not recommended"
  },
  "files": {
    "footprint": "cern_rn_50m_metallux_hvd_967_15_51_b_50m_1_1000_1_tc_50_25.kicad_mod",
    "symbol": "cern_rn_50m_metallux_hvd_967_15_51_b_50m_1_1000_1_tc_50_25.kicad_sym",
    "footprint_svg": "cern_rn_50m_metallux_hvd_967_15_51_b_50m_1_1000_1_tc_50_25.footprint.svg",
    "symbol_svg": "cern_rn_50m_metallux_hvd_967_15_51_b_50m_1_1000_1_tc_50_25.symbol.svg"
  },
  "formats": [
    "kicad_mod",
    "kicad_sym"
  ],
  "datasheet": "https://gitlab.com/ohwr/cern-kicad-libs/-/blob/master/SchLib/Resistors.kicad_sym",
  "dimensions_source": "cern-kicad-libs@53054c17 (Networks THD.pretty/RN_METALLUX_HVD 967.15.51.kicad_mod)",
  "verified": true,
  "origin": "imported",
  "tier": "verified-2d",
  "license": "CERN-OHL-P-2.0",
  "generated_by": "generators/import_cern.py",
  "keywords": [
    "cern",
    "high",
    "voltage",
    "divider",
    "hvd",
    "series",
    "967"
  ],
  "import": {
    "source_repo": "https://gitlab.com/ohwr/cern-kicad-libs",
    "source_commit": "53054c17",
    "source_files": {
      "db": "CERN.sqlite#Resistor Networks THD#RN_50M_METALLUX_HVD 967.15.51 B 50M 1_1000 1% TC 50/25",
      "symbol": "SchLib/Resistors.kicad_sym#RN Div - 1% R1=50M R2=50K",
      "footprint": "PcbLib/Networks THD.pretty/RN_METALLUX_HVD 967.15.51.kicad_mod"
    },
    "attribution": "CERN (kicad-dev@cern.ch), CERN-OHL-P-2.0",
    "import_date": "2026-07-05",
    "modifications": [
      "extracted single symbol from library",
      "stripped dead 3D model reference (upstream ships no 3D)",
      "auto-added courtyard (pads+outline+poly bbox +0.25mm)"
    ]
  }
}