{
  "id": "cern_12a48s",
  "name": "12A48S (CERN library)",
  "category": "power",
  "family": "CERN DC-DC Converters",
  "manufacturer": "PICO ELECTRONICS",
  "mpn_pattern": "12A48S",
  "description": "12VDC to 48VDC, Iout (max) 26mA, 1.25W High Reliability and Ultra-Miniature, Low Profile DC-DC Converter. Imported from the CERN KiCad library (CERN-OHL-P-2.0, (c) CERN); passed PartReel quality gates. Verified-2D part: upstream ships no 3D models.",
  "parameters": {
    "contacts": "4"
  },
  "files": {
    "footprint": "cern_12a48s.kicad_mod",
    "symbol": "cern_12a48s.kicad_sym",
    "footprint_svg": "cern_12a48s.footprint.svg",
    "symbol_svg": "cern_12a48s.symbol.svg"
  },
  "formats": [
    "kicad_mod",
    "kicad_sym"
  ],
  "datasheet": "https://gitlab.com/ohwr/cern-kicad-libs/-/blob/master/SchLib/DC-DC Converters.kicad_sym",
  "dimensions_source": "cern-kicad-libs@53054c17 (ICs And Semiconductors THD.pretty/DCDC_PICO_A_48V.kicad_mod)",
  "verified": true,
  "origin": "imported",
  "tier": "verified-2d",
  "license": "CERN-OHL-P-2.0",
  "generated_by": "generators/import_cern.py",
  "keywords": [
    "cern",
    "12vdc",
    "48vdc",
    "iout",
    "max",
    "26ma",
    "25w"
  ],
  "import": {
    "source_repo": "https://gitlab.com/ohwr/cern-kicad-libs",
    "source_commit": "53054c17",
    "source_files": {
      "db": "CERN.sqlite#DC-DC Converters#12A48S",
      "symbol": "SchLib/DC-DC Converters.kicad_sym#DCDC_PICO_A_Single Output",
      "footprint": "PcbLib/ICs And Semiconductors THD.pretty/DCDC_PICO_A_48V.kicad_mod"
    },
    "attribution": "CERN (kicad-dev@cern.ch), CERN-OHL-P-2.0",
    "import_date": "2026-07-05",
    "modifications": [
      "extracted single symbol from library",
      "stripped dead 3D model reference (upstream ships no 3D)",
      "auto-added courtyard (pads+outline+poly bbox +0.25mm)"
    ]
  }
}