{
  "id": "cern_hcnw139_000e",
  "name": "HCNW139-000E (CERN library)",
  "category": "ic",
  "family": "CERN Optocouplers",
  "manufacturer": "AVAGO TECHNOLOGIES",
  "mpn_pattern": "HCNW139-000E",
  "description": "Low Input Current, High Gain Optocoupler. Imported from the CERN KiCad library (CERN-OHL-P-2.0, (c) CERN); passed PartReel quality gates. 3D model generated parametrically from the IPC-7351 package name and the footprint's own pad geometry (PartReel).",
  "parameters": {
    "contacts": "8",
    "case": "DIP8W"
  },
  "files": {
    "footprint": "cern_hcnw139_000e.kicad_mod",
    "symbol": "cern_hcnw139_000e.kicad_sym",
    "footprint_svg": "cern_hcnw139_000e.footprint.svg",
    "symbol_svg": "cern_hcnw139_000e.symbol.svg",
    "model_3d": "cern_hcnw139_000e.step",
    "preview": "cern_hcnw139_000e.glb"
  },
  "formats": [
    "kicad_mod",
    "kicad_sym",
    "step",
    "glb"
  ],
  "datasheet": "https://gitlab.com/ohwr/cern-kicad-libs/-/blob/master/SchLib/Optocouplers.kicad_sym",
  "dimensions_source": "cern-kicad-libs@53054c17 (ICs And Semiconductors THD.pretty/DIP8-400.kicad_mod)",
  "verified": true,
  "origin": "imported",
  "license": "CERN-OHL-P-2.0",
  "generated_by": "generators/import_cern.py",
  "keywords": [
    "cern",
    "low",
    "input",
    "current",
    "high",
    "gain",
    "optocoupler"
  ],
  "import": {
    "source_repo": "https://gitlab.com/ohwr/cern-kicad-libs",
    "source_commit": "53054c17",
    "source_files": {
      "db": "CERN.sqlite#Optocouplers#HCNW139-000E",
      "symbol": "SchLib/Optocouplers.kicad_sym#Optocoupler Type5",
      "footprint": "PcbLib/ICs And Semiconductors THD.pretty/DIP8-400.kicad_mod"
    },
    "attribution": "CERN (kicad-dev@cern.ch), CERN-OHL-P-2.0",
    "import_date": "2026-07-05",
    "modifications": [
      "extracted single symbol from library",
      "stripped dead 3D model reference (upstream ships no 3D)",
      "auto-added courtyard (pads+outline+poly bbox +0.25mm)",
      "parametric 3D (STEP/GLB) generated by PartReel from IPC package name + pad geometry"
    ]
  },
  "asset_sha256": {
    "cern_hcnw139_000e.step": "e4e018f25f5178aa1b5c51bbfe15da3c8b19a5850ac201b502615e1a5dca1f5e",
    "cern_hcnw139_000e.glb": "e72b9749f20969d4af2fbfa857ef97553936f0b6d23468e0667f62fbc47683a1"
  }
}